photostats/__init__.py
photostats/__main__.py
photostats/camera.py
photostats/get_exif.py
photostats/lenses.py
photostats/tests/__init__.py
photostats/tests/test_get_exif.py
photostats/utils/__init__.py
photostats/utils/create_plot.py
photostats-0.8.1.dist-info/METADATA
photostats-0.8.1.dist-info/WHEEL
photostats-0.8.1.dist-info/top_level.txt
photostats-0.8.1.dist-info/RECORD
