Metadata-Version: 2.1
Name: photostats
Version: 0.8.1
Summary: Read directory containing photos and produce stats and graphs
Home-page: https://github.com/djotaku/photo_stats
Author: Eric Mesa
Author-email: eric@ericmesa.com
License: GPLv3
Keywords: photography
Platform: UNKNOWN
Classifier: Intended Audience :: End Users/Desktop
Classifier: License :: OSI Approved :: GNU General Public License v3 (GPLv3)
Classifier: Programming Language :: Python :: 3
Requires-Dist: matplotlib (==3.2.1)
Requires-Dist: pyexiv2 (==2.1.0)
